<annotation>
	<folder>collectedimages</folder>
	<filename>iloveyou.3130c4d4-aa79-11ec-9ab1-40a8f0002996.jpg</filename>
	<path>C:\Users\HP-1\realtimeobjectdetection\Tensorflow\workspace\images\collectedimages\iloveyou.3130c4d4-aa79-11ec-9ab1-40a8f0002996.jpg</path>
	<source>
		<database>Unknown</database>
	</source>
	<size>
		<width>640</width>
		<height>480</height>
		<depth>3</depth>
	</size>
	<segmented>0</segmented>
	<object>
		<name>I_Love_u</name>
		<pose>Unspecified</pose>
		<truncated>0</truncated>
		<difficult>0</difficult>
		<bndbox>
			<xmin>365</xmin>
			<ymin>175</ymin>
			<xmax>586</xmax>
			<ymax>434</ymax>
		</bndbox>
	</object>
</annotation>
